pytgcalls/__init__.py
pytgcalls/action.py
pytgcalls/dispatcher.py
pytgcalls/dispatcher_mixin.py
pytgcalls/group_call.py
pytgcalls/group_call_device.py
pytgcalls/group_call_native.py
pytgcalls/group_call_raw.py
pytgcalls-0.0.20.dist-info/LICENSE
pytgcalls-0.0.20.dist-info/METADATA
pytgcalls-0.0.20.dist-info/WHEEL
pytgcalls-0.0.20.dist-info/top_level.txt
pytgcalls-0.0.20.dist-info/RECORD
