Metadata-Version: 2.1
Name: pytgcalls
Version: 0.0.20
Summary: Library connecting python binding for tgcalls and pyrogram
Home-page: https://github.com/MarshalX/tgcalls
Author: Il`ya Semyonov
Author-email: ilya@marshal.dev
License: LGPLv3
Project-URL: Author, https://github.com/MarshalX
Project-URL: Telegram Channel, https://t.me/tgcallslib
Project-URL: Telegram Chat, https://t.me/tgcallschat
Keywords: python,library,telegram,async,asynchronous,webrtc,lib,voice-chat,voip,group-chat,video-call,calls,pyrogram,pytgcalls,tgcalls
Platform: UNKNOWN
Classifier: Development Status :: 4 - Beta
Classifier: Natural Language :: English
Classifier: Intended Audience :: Developers
Classifier: License :: OSI Approved :: GNU Lesser General Public License v3 (LGPLv3)
Classifier: Operating System :: OS Independent
Classifier: Topic :: Internet
Classifier: Topic :: Multimedia
Classifier: Topic :: Multimedia :: Video
Classifier: Topic :: Multimedia :: Video :: Capture
Classifier: Topic :: Multimedia :: Sound/Audio
Classifier: Topic :: Multimedia :: Sound/Audio :: Capture/Recording
Classifier: Topic :: Communications
Classifier: Topic :: Communications :: Internet Phone
Classifier: Topic :: Communications :: Telephony
Classifier: Topic :: Software Development :: Libraries
Classifier: Topic :: Software Development :: Libraries :: Python Modules
Classifier: Programming Language :: Python
Classifier: Programming Language :: Python :: 3
Classifier: Programming Language :: Python :: 3 :: Only
Classifier: Programming Language :: Python :: 3.6
Classifier: Programming Language :: Python :: 3.7
Classifier: Programming Language :: Python :: 3.8
Classifier: Programming Language :: Python :: 3.9
Classifier: Programming Language :: Python :: Implementation
Classifier: Programming Language :: Python :: Implementation :: CPython
Requires-Python: ~=3.6
Requires-Dist: tgcalls (==0.0.13)
Requires-Dist: pyrogram (>=1.2.0)
